{"character":"greninja","display_name":"Greninja","tier":"A-","weight":88,"playstyle_summary":"高い機動力と水手裏剣で戦うスピードファイター。空中機動力とダッシュ速度がトップクラス。影打ち(下B)での奇襲とコンボからの撃墜が強力。","key_strengths":[{"strength":"機動力","explanation_friendly":"走る速度も空中移動も全キャラトップクラスに速い。自由に動き回れる。","explanation_detailed":"走行速度2.288は全キャラ上位。空中横移動1.18も高水準。"},{"strength":"水手裏剣牽制","explanation_friendly":"溜められる飛び道具。牽制に使いやすくて相手の動きを制限できる。","explanation_detailed":"NB(水手裏剣)は溜め可能。小さいものから大きいものまで状況に応じて使い分けられる。"},{"strength":"コンボからの撃墜","explanation_friendly":"空上のお手玉からの撃墜が強い。ドラッグダウンからの追撃も。","explanation_detailed":"空上ドラッグダウン→上スマが中%で撃墜確定。空上ループからの火力も高い。"}],"key_weaknesses":[{"weakness":"近距離の発生が普通","explanation_friendly":"速いけど技の出は普通。密着の殴り合いでは有利にならない。","explanation_detailed":"弱3F、掴み6F。発生は平均的でインファイトの強さは機動力ほどではない。"},{"weakness":"軽い","explanation_friendly":"体重88は軽め。パワーキャラの一撃で飛ぶ。","explanation_detailed":"重量88は中量級下位。早期撃墜されやすい。"},{"weakness":"撃墜がやや不安定","explanation_friendly":"撃墜確定コンボはあるけど、素の撃墜力は高くない。","explanation_detailed":"空後(130%〜)、上スマ(130%〜)。確定コンボ以外の撃墜手段が限定的。"}]}