{
  "slug": "pac_man",
  "display_name": "Pac-Man",
  "source_url": "https://ultimateframedata.com/pac_man",
  "stats": {
    "weight": "Weight — 95",
    "gravity": "Gravity — 0.072",
    "walk speed": "Walk Speed — 1.097",
    "run speed": "Run Speed — 1.672",
    "initial dash": "Initial Dash — 1.87",
    "air speed": "Air Speed — 1.092",
    "air acceleration": "Total Air Acceleration — 0.08",
    "sh / fh / shff / fhff": "SH / FH / SHFF / FHFF Frames — 42 / 59 / 29 / 41",
    "fall speed": "Fall Speed / Fast Fall Speed — 1.35 / 2.16",
    "fast fall speed": "Fall Speed / Fast Fall Speed — 1.35 / 2.16"
  },
  "moves": [
    {
      "name": "Jab 1",
      "category": "ground_attacks",
      "startup": "4",
      "active_frames": "19",
      "total_frames": "--",
      "landing_lag": "Transitions to jab 2 as early as frame 7",
      "on_shield": "2.0",
      "damage": "7",
      "base_knockback": "",
      "knockback_growth": "",
      "notes": "3 | -- | -12 | 4 | 15 | Jab 2 | 4 | 21 | -- | Transitions to jab 3 as early as frame 7 | 2.0 | 5 | 3 | -- | -14 | 4 | 17 | Jab 3 | 4 | 33 | -- | -- | 4.0 | 11 | 5 | -- | -24 | 4—5 | 28 | * Does Not Have Model Scaling * | * Does Not Have Model Scaling * | * Does Not Have Model Scaling * | Forward Tilt | 5 | 30 | -- | -- | 8.0 | 7 | 8 | -- | -17 | 5—7 | 23 | * Does Not Have Model Scaling * | Up Tilt | 7 | 24 | -- | Arm intangibile on frame 7-10 | 6.5 | 6 | 7 | -- | -10 | 7—10 | 14 | Down Tilt | 7 | 26 | -- | -- | 6.0 | 6 | 6 | -- | -13 | 7—9 | 17 | Dash Attack | 10/19/28/37 | 45 | -- | -- | 2.0 / 4.0 | 4/11 | 3/5 | Multi/Final | -3 | 10—11/19—20/28—29/37 | 8 | Forward Smash | 16 | 52 | -- | Charge hold is frame 4 | 16.0/9.0 | 10/7 | 11/7 | Early/Late | -25 | 16—18(19—29) | 23 | Up Smash | 11/15 | 49 | -- | Charge hold is frame 4 | 3.0/14.0 | 5/10 | 3/10 | -- | -24 | 11/15—17(18—28) | 21 | Down Smash | 15 | 54 | -- | Charge hold is frame 3 | 13.0/7.0 | 9/7 | 9/6 | Early/late | -30 | 15—17(18—28) | 26"
    },
    {
      "name": "Jab 1",
      "category": "ground_attacks",
      "startup": "4",
      "active_frames": "19",
      "total_frames": "--",
      "landing_lag": "Transitions to jab 2 as early as frame 7",
      "on_shield": "2.0",
      "damage": "7",
      "base_knockback": "",
      "knockback_growth": "",
      "notes": "3 | -- | -12 | 4 | 15"
    },
    {
      "name": "Jab 1",
      "category": "ground_attacks",
      "startup": "",
      "active_frames": "",
      "total_frames": "",
      "landing_lag": "",
      "on_shield": "",
      "damage": "",
      "base_knockback": "",
      "knockback_growth": "",
      "notes": ""
    },
    {
      "name": "Jab 2",
      "category": "ground_attacks",
      "startup": "4",
      "active_frames": "21",
      "total_frames": "--",
      "landing_lag": "Transitions to jab 3 as early as frame 7",
      "on_shield": "2.0",
      "damage": "5",
      "base_knockback": "",
      "knockback_growth": "",
      "notes": "3 | -- | -14 | 4 | 17"
    },
    {
      "name": "Jab 2",
      "category": "ground_attacks",
      "startup": "",
      "active_frames": "",
      "total_frames": "",
      "landing_lag": "",
      "on_shield": "",
      "damage": "",
      "base_knockback": "",
      "knockback_growth": "",
      "notes": ""
    },
    {
      "name": "Jab 3",
      "category": "ground_attacks",
      "startup": "4",
      "active_frames": "33",
      "total_frames": "--",
      "landing_lag": "--",
      "on_shield": "4.0",
      "damage": "11",
      "base_knockback": "",
      "knockback_growth": "",
      "notes": "5 | -- | -24 | 4—5 | 28"
    },
    {
      "name": "Jab 3",
      "category": "ground_attacks",
      "startup": "",
      "active_frames": "",
      "total_frames": "",
      "landing_lag": "",
      "on_shield": "",
      "damage": "",
      "base_knockback": "",
      "knockback_growth": "",
      "notes": ""
    },
    {
      "name": "* Does Not Have Model Scaling *",
      "category": "ground_attacks",
      "startup": "* Does Not Have Model Scaling *",
      "active_frames": "* Does Not Have Model Scaling *",
      "total_frames": "Forward Tilt",
      "landing_lag": "5",
      "on_shield": "30",
      "damage": "--",
      "base_knockback": "",
      "knockback_growth": "",
      "notes": "-- | 8.0 | 7 | 8 | -- | -17 | 5—7 | 23"
    },
    {
      "name": "Forward Tilt",
      "category": "ground_attacks",
      "startup": "",
      "active_frames": "",
      "total_frames": "",
      "landing_lag": "",
      "on_shield": "",
      "damage": "",
      "base_knockback": "",
      "knockback_growth": "",
      "notes": ""
    },
    {
      "name": "* Does Not Have Model Scaling *",
      "category": "ground_attacks",
      "startup": "Up Tilt",
      "active_frames": "7",
      "total_frames": "24",
      "landing_lag": "--",
      "on_shield": "Arm intangibile on frame 7-10",
      "damage": "6.5",
      "base_knockback": "",
      "knockback_growth": "",
      "notes": "6 | 7 | -- | -10 | 7—10 | 14"
    },
    {
      "name": "Up Tilt",
      "category": "ground_attacks",
      "startup": "",
      "active_frames": "",
      "total_frames": "",
      "landing_lag": "",
      "on_shield": "",
      "damage": "",
      "base_knockback": "",
      "knockback_growth": "",
      "notes": ""
    },
    {
      "name": "Down Tilt",
      "category": "ground_attacks",
      "startup": "7",
      "active_frames": "26",
      "total_frames": "--",
      "landing_lag": "--",
      "on_shield": "6.0",
      "damage": "6",
      "base_knockback": "",
      "knockback_growth": "",
      "notes": "6 | -- | -13 | 7—9 | 17"
    },
    {
      "name": "Down Tilt",
      "category": "ground_attacks",
      "startup": "",
      "active_frames": "",
      "total_frames": "",
      "landing_lag": "",
      "on_shield": "",
      "damage": "",
      "base_knockback": "",
      "knockback_growth": "",
      "notes": ""
    },
    {
      "name": "Dash Attack",
      "category": "ground_attacks",
      "startup": "10/19/28/37",
      "active_frames": "45",
      "total_frames": "--",
      "landing_lag": "--",
      "on_shield": "2.0 / 4.0",
      "damage": "4/11",
      "base_knockback": "",
      "knockback_growth": "",
      "notes": "3/5 | Multi/Final | -3 | 10—11/19—20/28—29/37 | 8"
    },
    {
      "name": "Dash Attack",
      "category": "ground_attacks",
      "startup": "",
      "active_frames": "",
      "total_frames": "",
      "landing_lag": "",
      "on_shield": "",
      "damage": "",
      "base_knockback": "",
      "knockback_growth": "",
      "notes": ""
    },
    {
      "name": "Forward Smash",
      "category": "ground_attacks",
      "startup": "16",
      "active_frames": "52",
      "total_frames": "--",
      "landing_lag": "Charge hold is frame 4",
      "on_shield": "16.0/9.0",
      "damage": "10/7",
      "base_knockback": "",
      "knockback_growth": "",
      "notes": "11/7 | Early/Late | -25 | 16—18(19—29) | 23"
    },
    {
      "name": "Forward Smash",
      "category": "ground_attacks",
      "startup": "",
      "active_frames": "",
      "total_frames": "",
      "landing_lag": "",
      "on_shield": "",
      "damage": "",
      "base_knockback": "",
      "knockback_growth": "",
      "notes": ""
    },
    {
      "name": "Up Smash",
      "category": "ground_attacks",
      "startup": "11/15",
      "active_frames": "49",
      "total_frames": "--",
      "landing_lag": "Charge hold is frame 4",
      "on_shield": "3.0/14.0",
      "damage": "5/10",
      "base_knockback": "",
      "knockback_growth": "",
      "notes": "3/10 | -- | -24 | 11/15—17(18—28) | 21"
    },
    {
      "name": "Up Smash",
      "category": "ground_attacks",
      "startup": "",
      "active_frames": "",
      "total_frames": "",
      "landing_lag": "",
      "on_shield": "",
      "damage": "",
      "base_knockback": "",
      "knockback_growth": "",
      "notes": ""
    },
    {
      "name": "Down Smash",
      "category": "ground_attacks",
      "startup": "15",
      "active_frames": "54",
      "total_frames": "--",
      "landing_lag": "Charge hold is frame 3",
      "on_shield": "13.0/7.0",
      "damage": "9/7",
      "base_knockback": "",
      "knockback_growth": "",
      "notes": "9/6 | Early/late | -30 | 15—17(18—28) | 26"
    },
    {
      "name": "Down Smash",
      "category": "ground_attacks",
      "startup": "",
      "active_frames": "",
      "total_frames": "",
      "landing_lag": "",
      "on_shield": "",
      "damage": "",
      "base_knockback": "",
      "knockback_growth": "",
      "notes": ""
    },
    {
      "name": "* Missing Model Scaling *",
      "category": "aerial_attacks",
      "startup": "Neutral Air",
      "active_frames": "3",
      "total_frames": "51",
      "landing_lag": "7",
      "on_shield": "Autocancels on frame 1-2 and 45 onward",
      "damage": "10.0/6.0",
      "base_knockback": "",
      "knockback_growth": "",
      "notes": "8/6 | 4/3 | Early/Late | -3/-4 | 3—5(6—9/10—19) | FH | FH | 32 | Forward Air | 5 | 25 | 10 | Autocancels on frame 26 onward | 7.6 | 7 | 4 | -- | -6 | 5—8 | SH, FH, SHFF, FHFF | SH, FH, SHFF, FHFF | 17 | Back Air | 9 | 40 | 13 | Autocancels on frame 1-8 and 36 onward | 11.8/7.0 | 9/7 | 5/3 | Early/Late | -8/-10 | 9—11(12—16) | SH, FH, FHFF | SH, FH, FHFF | 24 | Up Air | 9 | 36 | 10 | Autocancels on frame 32 onward | 10.0 | 8 | 4 | -- | -6 | 9—16 | SH, FH, FHFF | SH, FH, FHFF | 20 | Down Air | 6/13/20/27 | 49 | 12 | Autocancels on frame 50 onward | 2.0/7.0 | 4/7 | 2/3 | Multi/Final | -10/-9 | 6—7/13—14/20—21/27—28 | FH | FH | 21"
    },
    {
      "name": "* Missing Model Scaling *",
      "category": "aerial_attacks",
      "startup": "Neutral Air",
      "active_frames": "3",
      "total_frames": "51",
      "landing_lag": "7",
      "on_shield": "Autocancels on frame 1-2 and 45 onward",
      "damage": "10.0/6.0",
      "base_knockback": "",
      "knockback_growth": "",
      "notes": "8/6 | 4/3 | Early/Late | -3/-4 | 3—5(6—9/10—19) | FH | FH | 32"
    },
    {
      "name": "Neutral Air",
      "category": "aerial_attacks",
      "startup": "",
      "active_frames": "",
      "total_frames": "",
      "landing_lag": "",
      "on_shield": "",
      "damage": "",
      "base_knockback": "",
      "knockback_growth": "",
      "notes": ""
    },
    {
      "name": "Forward Air",
      "category": "aerial_attacks",
      "startup": "5",
      "active_frames": "25",
      "total_frames": "10",
      "landing_lag": "Autocancels on frame 26 onward",
      "on_shield": "7.6",
      "damage": "7",
      "base_knockback": "",
      "knockback_growth": "",
      "notes": "4 | -- | -6 | 5—8 | SH, FH, SHFF, FHFF | SH, FH, SHFF, FHFF | 17"
    },
    {
      "name": "Forward Air",
      "category": "aerial_attacks",
      "startup": "",
      "active_frames": "",
      "total_frames": "",
      "landing_lag": "",
      "on_shield": "",
      "damage": "",
      "base_knockback": "",
      "knockback_growth": "",
      "notes": ""
    },
    {
      "name": "Back Air",
      "category": "aerial_attacks",
      "startup": "9",
      "active_frames": "40",
      "total_frames": "13",
      "landing_lag": "Autocancels on frame 1-8 and 36 onward",
      "on_shield": "11.8/7.0",
      "damage": "9/7",
      "base_knockback": "",
      "knockback_growth": "",
      "notes": "5/3 | Early/Late | -8/-10 | 9—11(12—16) | SH, FH, FHFF | SH, FH, FHFF | 24"
    },
    {
      "name": "Back Air",
      "category": "aerial_attacks",
      "startup": "",
      "active_frames": "",
      "total_frames": "",
      "landing_lag": "",
      "on_shield": "",
      "damage": "",
      "base_knockback": "",
      "knockback_growth": "",
      "notes": ""
    },
    {
      "name": "Up Air",
      "category": "aerial_attacks",
      "startup": "9",
      "active_frames": "36",
      "total_frames": "10",
      "landing_lag": "Autocancels on frame 32 onward",
      "on_shield": "10.0",
      "damage": "8",
      "base_knockback": "",
      "knockback_growth": "",
      "notes": "4 | -- | -6 | 9—16 | SH, FH, FHFF | SH, FH, FHFF | 20"
    },
    {
      "name": "Up Air",
      "category": "aerial_attacks",
      "startup": "",
      "active_frames": "",
      "total_frames": "",
      "landing_lag": "",
      "on_shield": "",
      "damage": "",
      "base_knockback": "",
      "knockback_growth": "",
      "notes": ""
    },
    {
      "name": "Down Air",
      "category": "aerial_attacks",
      "startup": "6/13/20/27",
      "active_frames": "49",
      "total_frames": "12",
      "landing_lag": "Autocancels on frame 50 onward",
      "on_shield": "2.0/7.0",
      "damage": "4/7",
      "base_knockback": "",
      "knockback_growth": "",
      "notes": "2/3 | Multi/Final | -10/-9 | 6—7/13—14/20—21/27—28 | FH | FH | 21"
    },
    {
      "name": "Down Air",
      "category": "aerial_attacks",
      "startup": "",
      "active_frames": "",
      "total_frames": "",
      "landing_lag": "",
      "on_shield": "",
      "damage": "",
      "base_knockback": "",
      "knockback_growth": "",
      "notes": ""
    },
    {
      "name": "Neutral B (Bonus Fruit, Throw)",
      "category": "special_attacks",
      "startup": "12(+7)",
      "active_frames": "41",
      "total_frames": "--",
      "landing_lag": "7 frames to enter charge state. 4 frames to cancel charge with shield. Fruits are Cherry (8), Strawberry (20), Lemon (32), Apple (52), Melon (72), Galaga (92), Bell (112), Key (132) Cherry, Strawberry, Lemon, Apple, and Melon linger for 32 frames after bouncing off somebody",
      "on_shield": "4.3 / 6.0 / 7.5 / 9.5 / 12.0 / 9.0 / 7.5 / 16.0",
      "damage": "5/6/7/8/9/7/7/10",
      "base_knockback": "",
      "knockback_growth": "",
      "notes": "2/3/3/4/4/4/3/5 | -- | -22/-20/-19/-17/-16/-18/-19/-14 | ** | -- | Early | Late | Side B (Power Pellet (Travel | Dash)) | 24—42 | 35—53 | 83—118 | -- | Only the dash's damage depends on level of charge. Knockback-based armor (100 units). | 4.0—5.0 | 6.0—12.0 | 5—6 | 6—9 | 5 | 6—11 | -- | -42 to -54 | ** | -- | Pac-Jump | Hurtbox | Up B (Pac-Jump) | 4 | -- | 30 | Trampoline can be interracted with as early as frame 10 and is unblockable. | 5.0—10.0 | 6—8 | 6—10 | first/second/third | ** | 4—12/13—16/17—21 | -- | Fall | Flying | Hurtbox | Down B (Fire Hydrant) | 12 | 34 | -- | -- | 9.0/13.0 | 7/9 | 4/5 | initial/launched | -11 | ** | --"
    },
    {
      "name": "Neutral B (Bonus Fruit, Throw)",
      "category": "special_attacks",
      "startup": "12(+7)",
      "active_frames": "41",
      "total_frames": "--",
      "landing_lag": "7 frames to enter charge state. 4 frames to cancel charge with shield. Fruits are Cherry (8), Strawberry (20), Lemon (32), Apple (52), Melon (72), Galaga (92), Bell (112), Key (132) Cherry, Strawberry, Lemon, Apple, and Melon linger for 32 frames after bouncing off somebody",
      "on_shield": "4.3 / 6.0 / 7.5 / 9.5 / 12.0 / 9.0 / 7.5 / 16.0",
      "damage": "5/6/7/8/9/7/7/10",
      "base_knockback": "",
      "knockback_growth": "",
      "notes": "2/3/3/4/4/4/3/5 | -- | -22/-20/-19/-17/-16/-18/-19/-14 | ** | --"
    },
    {
      "name": "Neutral B (Bonus Fruit, Throw)",
      "category": "special_attacks",
      "startup": "",
      "active_frames": "",
      "total_frames": "",
      "landing_lag": "",
      "on_shield": "",
      "damage": "",
      "base_knockback": "",
      "knockback_growth": "",
      "notes": ""
    },
    {
      "name": "Early",
      "category": "special_attacks",
      "startup": "Late",
      "active_frames": "Side B (Power Pellet (Travel | Dash))",
      "total_frames": "24—42 | 35—53",
      "landing_lag": "83—118",
      "on_shield": "--",
      "damage": "Only the dash's damage depends on level of charge. Knockback-based armor (100 units).",
      "base_knockback": "",
      "knockback_growth": "",
      "notes": "4.0—5.0 | 6.0—12.0 | 5—6 | 6—9 | 5 | 6—11 | -- | -42 to -54 | ** | --"
    },
    {
      "name": "Side B (Power Pellet (Travel | Dash))",
      "category": "special_attacks",
      "startup": "",
      "active_frames": "",
      "total_frames": "",
      "landing_lag": "",
      "on_shield": "",
      "damage": "",
      "base_knockback": "",
      "knockback_growth": "",
      "notes": ""
    },
    {
      "name": "Pac-Jump",
      "category": "special_attacks",
      "startup": "Hurtbox",
      "active_frames": "Up B (Pac-Jump)",
      "total_frames": "4",
      "landing_lag": "--",
      "on_shield": "30",
      "damage": "Trampoline can be interracted with as early as frame 10 and is unblockable.",
      "base_knockback": "",
      "knockback_growth": "",
      "notes": "5.0—10.0 | 6—8 | 6—10 | first/second/third | ** | 4—12/13—16/17—21 | --"
    },
    {
      "name": "Up B (Pac-Jump)",
      "category": "special_attacks",
      "startup": "",
      "active_frames": "",
      "total_frames": "",
      "landing_lag": "",
      "on_shield": "",
      "damage": "",
      "base_knockback": "",
      "knockback_growth": "",
      "notes": ""
    },
    {
      "name": "Fall",
      "category": "special_attacks",
      "startup": "Flying",
      "active_frames": "Hurtbox",
      "total_frames": "Down B (Fire Hydrant)",
      "landing_lag": "12",
      "on_shield": "34",
      "damage": "--",
      "base_knockback": "",
      "knockback_growth": "",
      "notes": "-- | 9.0/13.0 | 7/9 | 4/5 | initial/launched | -11 | ** | --"
    },
    {
      "name": "Down B (Fire Hydrant)",
      "category": "special_attacks",
      "startup": "",
      "active_frames": "",
      "total_frames": "",
      "landing_lag": "",
      "on_shield": "",
      "damage": "",
      "base_knockback": "",
      "knockback_growth": "",
      "notes": ""
    },
    {
      "name": "Grab",
      "category": "grabs_throws",
      "startup": "12",
      "active_frames": "58",
      "total_frames": "--",
      "landing_lag": "--",
      "on_shield": "--",
      "damage": "12—33",
      "base_knockback": "",
      "knockback_growth": "",
      "notes": "25 | Dash Grab | 14 | 66 | -- | -- | -- | 14—35 | 31 | Pivot Grab | 15 | 61 | -- | -- | -- | 15—36 | 25 | Pummel | 1 | 19 | -- | Total frames includes 13 frames of hitlag | 1.3 | Forward Throw | 13 | 33 | -- | -- | 8.0 | Backward Throw | 25 | 59 | -- | -- | 11.0 | Up Throw | 18 | 37 | -- | -- | 5.0 | Down Throw | 16/24/32/34 | 64 | -- | multi/final | 1.5/6.0"
    },
    {
      "name": "Grab",
      "category": "grabs_throws",
      "startup": "12",
      "active_frames": "58",
      "total_frames": "--",
      "landing_lag": "--",
      "on_shield": "--",
      "damage": "12—33",
      "base_knockback": "",
      "knockback_growth": "",
      "notes": "25"
    },
    {
      "name": "Grab",
      "category": "grabs_throws",
      "startup": "",
      "active_frames": "",
      "total_frames": "",
      "landing_lag": "",
      "on_shield": "",
      "damage": "",
      "base_knockback": "",
      "knockback_growth": "",
      "notes": ""
    },
    {
      "name": "Dash Grab",
      "category": "grabs_throws",
      "startup": "14",
      "active_frames": "66",
      "total_frames": "--",
      "landing_lag": "--",
      "on_shield": "--",
      "damage": "14—35",
      "base_knockback": "",
      "knockback_growth": "",
      "notes": "31"
    },
    {
      "name": "Dash Grab",
      "category": "grabs_throws",
      "startup": "",
      "active_frames": "",
      "total_frames": "",
      "landing_lag": "",
      "on_shield": "",
      "damage": "",
      "base_knockback": "",
      "knockback_growth": "",
      "notes": ""
    },
    {
      "name": "Pivot Grab",
      "category": "grabs_throws",
      "startup": "15",
      "active_frames": "61",
      "total_frames": "--",
      "landing_lag": "--",
      "on_shield": "--",
      "damage": "15—36",
      "base_knockback": "",
      "knockback_growth": "",
      "notes": "25"
    },
    {
      "name": "Pivot Grab",
      "category": "grabs_throws",
      "startup": "",
      "active_frames": "",
      "total_frames": "",
      "landing_lag": "",
      "on_shield": "",
      "damage": "",
      "base_knockback": "",
      "knockback_growth": "",
      "notes": ""
    },
    {
      "name": "Pummel",
      "category": "grabs_throws",
      "startup": "1",
      "active_frames": "19",
      "total_frames": "--",
      "landing_lag": "Total frames includes 13 frames of hitlag",
      "on_shield": "1.3",
      "damage": "",
      "base_knockback": "",
      "knockback_growth": "",
      "notes": ""
    },
    {
      "name": "Pummel",
      "category": "grabs_throws",
      "startup": "",
      "active_frames": "",
      "total_frames": "",
      "landing_lag": "",
      "on_shield": "",
      "damage": "",
      "base_knockback": "",
      "knockback_growth": "",
      "notes": ""
    },
    {
      "name": "Forward Throw",
      "category": "grabs_throws",
      "startup": "13",
      "active_frames": "33",
      "total_frames": "--",
      "landing_lag": "--",
      "on_shield": "8.0",
      "damage": "",
      "base_knockback": "",
      "knockback_growth": "",
      "notes": ""
    },
    {
      "name": "Forward Throw",
      "category": "grabs_throws",
      "startup": "",
      "active_frames": "",
      "total_frames": "",
      "landing_lag": "",
      "on_shield": "",
      "damage": "",
      "base_knockback": "",
      "knockback_growth": "",
      "notes": ""
    },
    {
      "name": "Backward Throw",
      "category": "grabs_throws",
      "startup": "25",
      "active_frames": "59",
      "total_frames": "--",
      "landing_lag": "--",
      "on_shield": "11.0",
      "damage": "",
      "base_knockback": "",
      "knockback_growth": "",
      "notes": ""
    },
    {
      "name": "Backward Throw",
      "category": "grabs_throws",
      "startup": "",
      "active_frames": "",
      "total_frames": "",
      "landing_lag": "",
      "on_shield": "",
      "damage": "",
      "base_knockback": "",
      "knockback_growth": "",
      "notes": ""
    },
    {
      "name": "Up Throw",
      "category": "grabs_throws",
      "startup": "18",
      "active_frames": "37",
      "total_frames": "--",
      "landing_lag": "--",
      "on_shield": "5.0",
      "damage": "",
      "base_knockback": "",
      "knockback_growth": "",
      "notes": ""
    },
    {
      "name": "Up Throw",
      "category": "grabs_throws",
      "startup": "",
      "active_frames": "",
      "total_frames": "",
      "landing_lag": "",
      "on_shield": "",
      "damage": "",
      "base_knockback": "",
      "knockback_growth": "",
      "notes": ""
    },
    {
      "name": "Down Throw",
      "category": "grabs_throws",
      "startup": "16/24/32/34",
      "active_frames": "64",
      "total_frames": "--",
      "landing_lag": "multi/final",
      "on_shield": "1.5/6.0",
      "damage": "",
      "base_knockback": "",
      "knockback_growth": "",
      "notes": ""
    },
    {
      "name": "Down Throw",
      "category": "grabs_throws",
      "startup": "",
      "active_frames": "",
      "total_frames": "",
      "landing_lag": "",
      "on_shield": "",
      "damage": "",
      "base_knockback": "",
      "knockback_growth": "",
      "notes": ""
    },
    {
      "name": "Spot Dodge",
      "category": "dodges_rolls",
      "startup": "20/25",
      "active_frames": "--",
      "total_frames": "Intangible on frame 3-17",
      "landing_lag": "Forward Roll",
      "on_shield": "29",
      "damage": "--",
      "base_knockback": "",
      "knockback_growth": "",
      "notes": "Intangible on frame 4-15 | Backward Roll | 34 | -- | Intangible on frame 5-16 | Neutral Air Dodge | 55 | 10 | Intangible on frame 3-29 | Air Dodge, Down | 78 | 11-19 | Intangible on frame 3-21 | Air Dodge, Diagonally Down | 87 | 11-19 | Intangible on frame 3-21 | Air Dodge, Left/Right | 96 | 11-19 | Intangible on frame 3-21 | Air Dodge, Diagonally Up | 111 | 11-19 | Intangible on frame 3-21 | Air Dodge, Up | 130 | 11-19 | Intangible on frame 3-21"
    },
    {
      "name": "Spot Dodge",
      "category": "dodges_rolls",
      "startup": "20/25",
      "active_frames": "--",
      "total_frames": "Intangible on frame 3-17",
      "landing_lag": "",
      "on_shield": "",
      "damage": "",
      "base_knockback": "",
      "knockback_growth": "",
      "notes": ""
    },
    {
      "name": "Spot Dodge",
      "category": "dodges_rolls",
      "startup": "",
      "active_frames": "",
      "total_frames": "",
      "landing_lag": "",
      "on_shield": "",
      "damage": "",
      "base_knockback": "",
      "knockback_growth": "",
      "notes": ""
    },
    {
      "name": "Forward Roll",
      "category": "dodges_rolls",
      "startup": "29",
      "active_frames": "--",
      "total_frames": "Intangible on frame 4-15",
      "landing_lag": "",
      "on_shield": "",
      "damage": "",
      "base_knockback": "",
      "knockback_growth": "",
      "notes": ""
    },
    {
      "name": "Forward Roll",
      "category": "dodges_rolls",
      "startup": "",
      "active_frames": "",
      "total_frames": "",
      "landing_lag": "",
      "on_shield": "",
      "damage": "",
      "base_knockback": "",
      "knockback_growth": "",
      "notes": ""
    },
    {
      "name": "Backward Roll",
      "category": "dodges_rolls",
      "startup": "34",
      "active_frames": "--",
      "total_frames": "Intangible on frame 5-16",
      "landing_lag": "",
      "on_shield": "",
      "damage": "",
      "base_knockback": "",
      "knockback_growth": "",
      "notes": ""
    },
    {
      "name": "Backward Roll",
      "category": "dodges_rolls",
      "startup": "",
      "active_frames": "",
      "total_frames": "",
      "landing_lag": "",
      "on_shield": "",
      "damage": "",
      "base_knockback": "",
      "knockback_growth": "",
      "notes": ""
    },
    {
      "name": "Neutral Air Dodge",
      "category": "dodges_rolls",
      "startup": "55",
      "active_frames": "10",
      "total_frames": "Intangible on frame 3-29",
      "landing_lag": "",
      "on_shield": "",
      "damage": "",
      "base_knockback": "",
      "knockback_growth": "",
      "notes": ""
    },
    {
      "name": "Neutral Air Dodge",
      "category": "dodges_rolls",
      "startup": "",
      "active_frames": "",
      "total_frames": "",
      "landing_lag": "",
      "on_shield": "",
      "damage": "",
      "base_knockback": "",
      "knockback_growth": "",
      "notes": ""
    },
    {
      "name": "Air Dodge, Down",
      "category": "dodges_rolls",
      "startup": "78",
      "active_frames": "11-19",
      "total_frames": "Intangible on frame 3-21",
      "landing_lag": "",
      "on_shield": "",
      "damage": "",
      "base_knockback": "",
      "knockback_growth": "",
      "notes": ""
    },
    {
      "name": "Air Dodge, Down",
      "category": "dodges_rolls",
      "startup": "",
      "active_frames": "",
      "total_frames": "",
      "landing_lag": "",
      "on_shield": "",
      "damage": "",
      "base_knockback": "",
      "knockback_growth": "",
      "notes": ""
    },
    {
      "name": "Air Dodge, Diagonally Down",
      "category": "dodges_rolls",
      "startup": "87",
      "active_frames": "11-19",
      "total_frames": "Intangible on frame 3-21",
      "landing_lag": "",
      "on_shield": "",
      "damage": "",
      "base_knockback": "",
      "knockback_growth": "",
      "notes": ""
    },
    {
      "name": "Air Dodge, Diagonally Down",
      "category": "dodges_rolls",
      "startup": "",
      "active_frames": "",
      "total_frames": "",
      "landing_lag": "",
      "on_shield": "",
      "damage": "",
      "base_knockback": "",
      "knockback_growth": "",
      "notes": ""
    },
    {
      "name": "Air Dodge, Left/Right",
      "category": "dodges_rolls",
      "startup": "96",
      "active_frames": "11-19",
      "total_frames": "Intangible on frame 3-21",
      "landing_lag": "",
      "on_shield": "",
      "damage": "",
      "base_knockback": "",
      "knockback_growth": "",
      "notes": ""
    },
    {
      "name": "Air Dodge, Left/Right",
      "category": "dodges_rolls",
      "startup": "",
      "active_frames": "",
      "total_frames": "",
      "landing_lag": "",
      "on_shield": "",
      "damage": "",
      "base_knockback": "",
      "knockback_growth": "",
      "notes": ""
    },
    {
      "name": "Air Dodge, Diagonally Up",
      "category": "dodges_rolls",
      "startup": "111",
      "active_frames": "11-19",
      "total_frames": "Intangible on frame 3-21",
      "landing_lag": "",
      "on_shield": "",
      "damage": "",
      "base_knockback": "",
      "knockback_growth": "",
      "notes": ""
    },
    {
      "name": "Air Dodge, Diagonally Up",
      "category": "dodges_rolls",
      "startup": "",
      "active_frames": "",
      "total_frames": "",
      "landing_lag": "",
      "on_shield": "",
      "damage": "",
      "base_knockback": "",
      "knockback_growth": "",
      "notes": ""
    },
    {
      "name": "Air Dodge, Up",
      "category": "dodges_rolls",
      "startup": "130",
      "active_frames": "11-19",
      "total_frames": "Intangible on frame 3-21",
      "landing_lag": "",
      "on_shield": "",
      "damage": "",
      "base_knockback": "",
      "knockback_growth": "",
      "notes": ""
    },
    {
      "name": "Air Dodge, Up",
      "category": "dodges_rolls",
      "startup": "",
      "active_frames": "",
      "total_frames": "",
      "landing_lag": "",
      "on_shield": "",
      "damage": "",
      "base_knockback": "",
      "knockback_growth": "",
      "notes": ""
    },
    {
      "name": "Stats",
      "category": "misc_info",
      "startup": "Weight — 95",
      "active_frames": "Gravity — 0.072",
      "total_frames": "Walk Speed — 1.097",
      "landing_lag": "Run Speed — 1.672",
      "on_shield": "Initial Dash — 1.87",
      "damage": "Air Speed — 1.092",
      "base_knockback": "",
      "knockback_growth": "",
      "notes": "Total Air Acceleration — 0.08 | SH / FH / SHFF / FHFF Frames — 42 / 59 / 29 / 41 | Fall Speed / Fast Fall Speed — 1.35 / 2.16 | Out of Shield, Up B — 4 frames | Out of Shield, Neutral Air — 6 frames | Out of Shield, Forward Air — 8 frames | Shield Grab (Grab, post-Shieldstun) — 16 frames | Shield Drop — 11 frames (universal) | Jump Squat (pre-Jump frames) — 3 frames (universal) | Ledge Grab | Normal | Ledge Hang | Getup Attacks | Facing Up | Facing Down | Trip | Ledge"
    },
    {
      "name": "Stats",
      "category": "misc_info",
      "startup": "Weight — 95",
      "active_frames": "Gravity — 0.072",
      "total_frames": "Walk Speed — 1.097",
      "landing_lag": "Run Speed — 1.672",
      "on_shield": "Initial Dash — 1.87",
      "damage": "Air Speed — 1.092",
      "base_knockback": "",
      "knockback_growth": "",
      "notes": "Total Air Acceleration — 0.08 | SH / FH / SHFF / FHFF Frames — 42 / 59 / 29 / 41 | Fall Speed / Fast Fall Speed — 1.35 / 2.16 | Out of Shield, Up B — 4 frames | Out of Shield, Neutral Air — 6 frames | Out of Shield, Forward Air — 8 frames | Shield Grab (Grab, post-Shieldstun) — 16 frames | Shield Drop — 11 frames (universal) | Jump Squat (pre-Jump frames) — 3 frames (universal)"
    },
    {
      "name": "Stats",
      "category": "misc_info",
      "startup": "",
      "active_frames": "",
      "total_frames": "",
      "landing_lag": "",
      "on_shield": "",
      "damage": "",
      "base_knockback": "",
      "knockback_growth": "",
      "notes": ""
    },
    {
      "name": "Ledge Grab",
      "category": "misc_info",
      "startup": "Normal",
      "active_frames": "",
      "total_frames": "",
      "landing_lag": "",
      "on_shield": "",
      "damage": "",
      "base_knockback": "",
      "knockback_growth": "",
      "notes": ""
    },
    {
      "name": "Ledge Grab",
      "category": "misc_info",
      "startup": "",
      "active_frames": "",
      "total_frames": "",
      "landing_lag": "",
      "on_shield": "",
      "damage": "",
      "base_knockback": "",
      "knockback_growth": "",
      "notes": ""
    },
    {
      "name": "Ledge Hang",
      "category": "misc_info",
      "startup": "",
      "active_frames": "",
      "total_frames": "",
      "landing_lag": "",
      "on_shield": "",
      "damage": "",
      "base_knockback": "",
      "knockback_growth": "",
      "notes": ""
    },
    {
      "name": "Ledge Hang",
      "category": "misc_info",
      "startup": "",
      "active_frames": "",
      "total_frames": "",
      "landing_lag": "",
      "on_shield": "",
      "damage": "",
      "base_knockback": "",
      "knockback_growth": "",
      "notes": ""
    },
    {
      "name": "Getup Attacks",
      "category": "misc_info",
      "startup": "Facing Up",
      "active_frames": "Facing Down",
      "total_frames": "Trip",
      "landing_lag": "Ledge",
      "on_shield": "",
      "damage": "",
      "base_knockback": "",
      "knockback_growth": "",
      "notes": ""
    },
    {
      "name": "Getup Attacks",
      "category": "misc_info",
      "startup": "",
      "active_frames": "",
      "total_frames": "",
      "landing_lag": "",
      "on_shield": "",
      "damage": "",
      "base_knockback": "",
      "knockback_growth": "",
      "notes": ""
    }
  ]
}