{
  "char_a": "mario",
  "char_b": "wolf",
  "perspective": "mario",
  "overall_rating": 0,
  "summary": "ほぼ五分。ウルフのブラスター牽制と中距離のコントロールvsマリオの近距離の回転力と上B OoS。マリオが懐に入れば有利、中距離でブラスターを食らう展開は不利。",
  "neutral_tips": [
    "ウルフのブラスターは7%+怯みあり。中距離で食らい続けると大幅不利。ジャンプかシールドで対処",
    "FB（ファイアボール）でブラスターの隙を叩く。FBとブラスターの撃ち合いは微妙にマリオ有利（FBは後隙が短い）",
    "FB→ダッシュ掴みが基本の差し込み。ウルフがブラスターを構えている時にFBで動かしてから掴む",
    "ウルフの空後はリーチと撃墜力が高い。中距離でRARを狙ってくるので、引きステップで空振りさせる"
  ],
  "advantage_tips": [
    "マリオのコンボは安定。下投げ→空上→空上で40%以上稼げる",
    "ウルフの復帰は弱い。FB+空前で復帰阻止すれば早期撃墜可能。マントで上Bの向きを反転させるのも強力",
    "上投げ→上B（100-130%で撃墜確定）がウルフの中量級の重さだと安定して入る"
  ],
  "disadvantage_tips": [
    "ウルフの下投げ→空後はマリオに対して90-110%で撃墜確定。掴まれないように注意",
    "ウルフのフラッシュ（横B）は90%付近から撃墜。大きな後隙がある技の後に合わせてくるので注意",
    "マリオの復帰をウルフの空後で阻止されやすい。復帰ルートを散らす"
  ],
  "kill_percent_notes": [
    "マリオの上投げ→上Bはウルフに対して100-130%で確定。掴みに行くことが最重要",
    "ウルフの下投げ→空後は90-110%でマリオを撃墜。お互いに掴みのリターンが高い",
    "マリオの後ろ投げは崖端120%〜で撃墜。位置取りに注意"
  ],
  "stage_preference": "小戦場がやや有利。台があるとマリオの空上が当てやすく、着地狩りの起点になる。ウルフのブラスターは台で遮られる場面もある"
}